tictactoe/__init__.py
tictactoe/engine.py
xando-0.0.3.dist-info/LICENSE
xando-0.0.3.dist-info/METADATA
xando-0.0.3.dist-info/WHEEL
xando-0.0.3.dist-info/top_level.txt
xando-0.0.3.dist-info/RECORD
