Metadata-Version: 2.1
Name: xando
Version: 0.0.3
Summary: TicTacToe game engine
Home-page: https://github.com/abstractpaper/tictactoe
Author: Aziz Alfoudari
Author-email: aziz.alfoudari@gmail.com
License: UNKNOWN
Platform: UNKNOWN
Classifier: Programming Language :: Python :: 3
Classifier: License :: OSI Approved :: MIT License
Classifier: Operating System :: OS Independent
Requires-Python: >=3.6
